rtl/riscv/rv128i_alu.sv
`timescale 1ns/1ps

module rv128i_alu (
    input  logic [127:0] a,
    input  logic [127:0] b,
    input  logic [3:0]   op,
    output logic [127:0] y,
    output logic         zero
);

    localparam ALU_ADD = 4'd0;
    localparam ALU_SUB = 4'd1;
    localparam ALU_AND = 4'd2;
    localparam ALU_OR  = 4'd3;
    localparam ALU_XOR = 4'd4;
    localparam ALU_SLL = 4'd5;
    localparam ALU_SRL = 4'd6;

    always_comb begin
        case (op)
            ALU_ADD: y = a + b;
            ALU_SUB: y = a - b;
            ALU_AND: y = a & b;
            ALU_OR : y = a | b;
            ALU_XOR: y = a ^ b;
            ALU_SLL: y = a << b[6:0];
            ALU_SRL: y = a >> b[6:0];
            default: y = '0;
        endcase

        zero = (y == 128'b0);
    end

endmodule

rtl/riscv/rv128i_regfile.sv
`timescale 1ns/1ps

module rv128i_regfile (
    input  logic         clk,
    input  logic         rst,

    input  logic [4:0]   rs1_addr,
    input  logic [4:0]   rs2_addr,
    output logic [127:0] rs1_data,
    output logic [127:0] rs2_data,

    input  logic         wr_en,
    input  logic [4:0]   rd_addr,
    input  logic [127:0] rd_data
);

    logic [127:0] regs [0:31];

    assign rs1_data = (rs1_addr == 5'd0) ? 128'd0 : regs[rs1_addr];
    assign rs2_data = (rs2_addr == 5'd0) ? 128'd0 : regs[rs2_addr];

    integer i;

    always_ff @(posedge clk or posedge rst) begin
        if (rst) begin
            for (i = 0; i < 32; i = i + 1)
                regs[i] <= 128'd0;
        end
        else begin
            regs[0] <= 128'd0;

            if (wr_en && (rd_addr != 5'd0))
                regs[rd_addr] <= rd_data;
        end
    end

endmodule

rtl/riscv/rv128i_decoder.sv
`timescale 1ns/1ps

module rv128i_decoder (
    input  logic [31:0] instr,

    output logic [6:0]  opcode,
    output logic [4:0]  rd,
    output logic [4:0]  rs1,
    output logic [4:0]  rs2,
    output logic [2:0]  funct3,
    output logic [6:0]  funct7,

    output logic [3:0]  alu_op,
    output logic        reg_write,
    output logic        mem_read,
    output logic        mem_write,
    output logic        branch,
    output logic        jump
);

    localparam ALU_ADD = 4'd0;
    localparam ALU_SUB = 4'd1;
    localparam ALU_AND = 4'd2;
    localparam ALU_OR  = 4'd3;
    localparam ALU_XOR = 4'd4;

    always_comb begin
        opcode    = instr[6:0];
        rd        = instr[11:7];
        funct3    = instr[14:12];
        rs1       = instr[19:15];
        rs2       = instr[24:20];
        funct7    = instr[31:25];

        alu_op    = ALU_ADD;
        reg_write = 1'b0;
        mem_read  = 1'b0;
        mem_write = 1'b0;
        branch    = 1'b0;
        jump      = 1'b0;

        case (opcode)

            // OP-IMM
            7'b0010011: begin
                reg_write = 1'b1;
                case (funct3)
                    3'b000: alu_op = ALU_ADD; // ADDI
                    3'b111: alu_op = ALU_AND; // ANDI
                    3'b110: alu_op = ALU_OR;  // ORI
                    3'b100: alu_op = ALU_XOR; // XORI
                    default: reg_write = 1'b0;
                endcase
            end

            // OP
            7'b0110011: begin
                reg_write = 1'b1;
                case ({funct7, funct3})
                    10'b0000000_000: alu_op = ALU_ADD; // ADD
                    10'b0100000_000: alu_op = ALU_SUB; // SUB
                    10'b0000000_111: alu_op = ALU_AND; // AND
                    10'b0000000_110: alu_op = ALU_OR;  // OR
                    10'b0000000_100: alu_op = ALU_XOR; // XOR
                    default: reg_write = 1'b0;
                endcase
            end

            // LOAD
            7'b0000011: begin
                mem_read  = 1'b1;
                reg_write = 1'b1;
                alu_op    = ALU_ADD;
            end

            // STORE
            7'b0100011: begin
                mem_write = 1'b1;
                alu_op    = ALU_ADD;
            end

            // BRANCH
            7'b1100011: begin
                branch = 1'b1;
                alu_op = ALU_SUB;
            end

            // JAL
            7'b1101111: begin
                jump      = 1'b1;
                reg_write = 1'b1;
            end

            // JALR
            7'b1100111: begin
                jump      = 1'b1;
                reg_write = 1'b1;
                alu_op    = ALU_ADD;
            end

            // LUI
            7'b0110111: begin
                reg_write = 1'b1;
            end

            // AUIPC
            7'b0010111: begin
                reg_write = 1'b1;
                alu_op    = ALU_ADD;
            end

            default: begin
                alu_op = ALU_ADD;
            end
        endcase
    end

endmodule

rtl/riscv/rv128i_pc.sv
`timescale 1ns/1ps

module rv128i_pc #(
    parameter logic [127:0] RESET_PC = 128'h0
) (
    input  logic         clk,
    input  logic         rst,
    input  logic         enable,
    input  logic         branch_taken,
    input  logic [127:0] branch_target,

    output logic [127:0] pc
);

    always_ff @(posedge clk or posedge rst) begin
        if (rst)
            pc <= RESET_PC;
        else if (enable) begin
            if (branch_taken)
                pc <= branch_target;
            else
                pc <= pc + 128'd4;
        end
    end

endmodule

rtl/riscv/rv128i_cpu.sv
`timescale 1ns/1ps

module rv128i_cpu (
    input  logic         clk,
    input  logic         rst,

    // Instruction memory
    output logic [127:0] imem_addr,
    input  logic [31:0]  imem_rdata,

    // 128-bit data / NoC interface
    output logic         dmem_valid,
    input  logic         dmem_ready,
    output logic         dmem_we,
    output logic [127:0] dmem_addr,
    output logic [127:0] dmem_wdata,
    input  logic [127:0] dmem_rdata,

    output logic         halted
);

    // ------------------------------------------------------------
    // PC / Fetch
    // ------------------------------------------------------------
    logic [127:0] pc;
    logic         branch_taken;
    logic [127:0] branch_target;

    rv128i_pc u_pc (
        .clk           (clk),
        .rst           (rst),
        .enable        (!halted),
        .branch_taken  (branch_taken),
        .branch_target (branch_target),
        .pc            (pc)
    );

    assign imem_addr = pc;

    // ------------------------------------------------------------
    // Instruction fields
    // ------------------------------------------------------------
    logic [31:0] instr;

    logic [6:0] opcode;
    logic [4:0] rd;
    logic [4:0] rs1;
    logic [4:0] rs2;
    logic [2:0] funct3;
    logic [6:0] funct7;

    logic [3:0] alu_op;
    logic       reg_write;
    logic       mem_read;
    logic       mem_write;
    logic       branch;
    logic       jump;

    assign instr = imem_rdata;

    rv128i_decoder u_decoder (
        .instr      (instr),
        .opcode     (opcode),
        .rd         (rd),
        .rs1        (rs1),
        .rs2        (rs2),
        .funct3     (funct3),
        .funct7     (funct7),
        .alu_op     (alu_op),
        .reg_write  (reg_write),
        .mem_read   (mem_read),
        .mem_write  (mem_write),
        .branch     (branch),
        .jump       (jump)
    );

    // ------------------------------------------------------------
    // Register file
    // ------------------------------------------------------------
    logic [127:0] rs1_data;
    logic [127:0] rs2_data;

    logic [127:0] writeback_data;

    rv128i_regfile u_regfile (
        .clk        (clk),
        .rst        (rst),
        .rs1_addr   (rs1),
        .rs2_addr   (rs2),
        .rs1_data   (rs1_data),
        .rs2_data   (rs2_data),
        .wr_en      (reg_write && !mem_read && !halted),
        .rd_addr    (rd),
        .rd_data    (writeback_data)
    );

    // ------------------------------------------------------------
    // Immediate generation
    // ------------------------------------------------------------
    logic [127:0] imm_i;
    logic [127:0] imm_s;
    logic [127:0] imm_b;
    logic [127:0] imm_u;
    logic [127:0] imm_j;

    always_comb begin
        imm_i = {{116{instr[31]}}, instr[31:20]};

        imm_s = {{116{instr[31]}},
                 instr[31:25],
                 instr[11:7]};

        imm_b = {{115{instr[31]}},
                 instr[31],
                 instr[7],
                 instr[30:25],
                 instr[11:8],
                 1'b0};

        imm_u = {{96{instr[31]}}, instr[31:12], 12'b0};

        imm_j = {{108{instr[31]}},
                 instr[31],
                 instr[19:12],
                 instr[20],
                 instr[30:21],
                 1'b0};
    end

    // ------------------------------------------------------------
    // ALU
    // ------------------------------------------------------------
    logic [127:0] alu_a;
    logic [127:0] alu_b;
    logic [127:0] alu_result;
    logic         alu_zero;

    always_comb begin
        alu_a = rs1_data;
        alu_b = rs2_data;

        if (mem_read)
            alu_b = imm_i;
        else if (mem_write)
            alu_b = imm_s;
        else if (opcode == 7'b0010011)
            alu_b = imm_i;

        if (opcode == 7'b0110111)
            alu_a = 128'd0;

        if (opcode == 7'b0010111)
            alu_a = pc;
    end

    rv128i_alu u_alu (
        .a    (alu_a),
        .b    (alu_b),
        .op   (alu_op),
        .y    (alu_result),
        .zero (alu_zero)
    );

    // ------------------------------------------------------------
    // Data / NoC interface
    // ------------------------------------------------------------
    always_comb begin
        dmem_valid = 1'b0;
        dmem_we    = 1'b0;
        dmem_addr  = 128'd0;
        dmem_wdata = 128'd0;

        if (!halted && (mem_read || mem_write)) begin
            dmem_valid = 1'b1;
            dmem_we    = mem_write;
            dmem_addr  = alu_result;
            dmem_wdata = rs2_data;
        end
    end

    // ------------------------------------------------------------
    // Writeback
    // ------------------------------------------------------------
    always_comb begin
        writeback_data = alu_result;

        if (mem_read)
            writeback_data = dmem_rdata;

        if (opcode == 7'b1101111 || opcode == 7'b1100111)
            writeback_data = pc + 128'd4;

        if (opcode == 7'b0110111)
            writeback_data = imm_u;

        if (opcode == 7'b0010111)
            writeback_data = pc + imm_u;
    end

    // ------------------------------------------------------------
    // Branch / jump control
    // ------------------------------------------------------------
    always_comb begin
        branch_taken = 1'b0;
        branch_target = pc + 128'd4;

        if (branch) begin
            case (funct3)
                3'b000: branch_taken = (rs1_data == rs2_data); // BEQ
                3'b001: branch_taken = (rs1_data != rs2_data); // BNE
                default: branch_taken = 1'b0;
            endcase

            branch_target = pc + imm_b;
        end

        if (jump) begin
            branch_taken = 1'b1;

            if (opcode == 7'b1101111)
                branch_target = pc + imm_j;
            else
                branch_target = (rs1_data + imm_i) & ~128'd1;
        end
    end

    // ------------------------------------------------------------
    // Halt
    // ------------------------------------------------------------
    logic halt_reg;

    always_ff @(posedge clk or posedge rst) begin
        if (rst)
            halt_reg <= 1'b0;
        else if (instr == 32'h00100073)
            halt_reg <= 1'b1;
    end

    assign halted = halt_reg;

endmodule

tb/riscv/tb_rv128i_cpu.sv
`timescale 1ns/1ps

module tb_rv128i_cpu;

    logic clk = 0;
    logic rst = 1;

    logic [127:0] imem_addr;
    logic [31:0]  imem_rdata;

    logic         dmem_valid;
    logic         dmem_ready;
    logic         dmem_we;
    logic [127:0] dmem_addr;
    logic [127:0] dmem_wdata;
    logic [127:0] dmem_rdata;

    logic halted;

    logic [31:0] imem [0:31];
    logic [127:0] memory [0:31];

    rv128i_cpu dut (
        .clk,
        .rst,
        .imem_addr,
        .imem_rdata,
        .dmem_valid,
        .dmem_ready,
        .dmem_we,
        .dmem_addr,
        .dmem_wdata,
        .dmem_rdata,
        .halted
    );

    always #5 clk = ~clk;

    assign imem_rdata = imem[imem_addr[6:2]];
    assign dmem_rdata = memory[dmem_addr[6:2]];
    assign dmem_ready = dmem_valid;

    always_ff @(posedge clk) begin
        if (!rst && dmem_valid && dmem_we)
            memory[dmem_addr[6:2]] <= dmem_wdata;
    end

    initial begin
        integer i;

        for (i = 0; i < 32; i = i + 1) begin
            imem[i]   = 32'h00000013; // NOP
            memory[i] = 128'd0;
        end

        // ADDI x1, x0, 10
        imem[0] = 32'h00A00093;

        // ADDI x2, x0, 5
        imem[1] = 32'h00500113;

        // ADD x3, x1, x2
        imem[2] = 32'h002081B3;

        // EBREAK
        imem[3] = 32'h00100073;

        repeat (2) @(posedge clk);
        #1;
        rst = 0;

        wait (halted);
        #2;

        $display("========================================");
        $display("        RV128I CPU TEST");
        $display("========================================");

        $display("x1 = %0d", dut.u_regfile.regs[1]);
        $display("x2 = %0d", dut.u_regfile.regs[2]);
        $display("x3 = %0d", dut.u_regfile.regs[3]);

        if (dut.u_regfile.regs[1] == 128'd10 &&
            dut.u_regfile.regs[2] == 128'd5 &&
            dut.u_regfile.regs[3] == 128'd15) begin

            $display("***** RV128I CPU TEST PASS *****");

        end else begin

            $display("***** RV128I CPU TEST FAIL *****");
            $fatal(1);

        end

        $finish;
    end
        initial begin
        $dumpfile("results/riscv/rv128i_cpu_wave.vcd");
        $dumpvars(0, tb_rv128i_cpu);
    end
endmodule

results/riscv/rv128i_cpu_wave.vcd
$date
	Mon Oct  5 18:36:19 2026
$end
$version
	Icarus Verilog
$end
$timescale
	1ps
$end
$scope module tb_rv128i_cpu $end
$var wire 128 ! dmem_rdata [127:0] $end
$var wire 1 " dmem_ready $end
$var wire 32 # imem_rdata [31:0] $end
$var wire 128 $ imem_addr [127:0] $end
$var wire 1 % halted $end
$var wire 1 & dmem_we $end
$var wire 128 ' dmem_wdata [127:0] $end
$var wire 1 ( dmem_valid $end
$var wire 128 ) dmem_addr [127:0] $end
$var reg 1 * clk $end
$var reg 1 + rst $end
$scope module dut $end
$var wire 1 * clk $end
$var wire 128 , dmem_rdata [127:0] $end
$var wire 1 " dmem_ready $end
$var wire 1 % halted $end
$var wire 128 - imem_addr [127:0] $end
$var wire 32 . imem_rdata [31:0] $end
$var wire 32 / instr [31:0] $end
$var wire 1 + rst $end
$var wire 128 0 rs2_data [127:0] $end
$var wire 5 1 rs2 [4:0] $end
$var wire 128 2 rs1_data [127:0] $end
$var wire 5 3 rs1 [4:0] $end
$var wire 1 4 reg_write $end
$var wire 5 5 rd [4:0] $end
$var wire 128 6 pc [127:0] $end
$var wire 7 7 opcode [6:0] $end
$var wire 1 8 mem_write $end
$var wire 1 9 mem_read $end
$var wire 1 : jump $end
$var wire 7 ; funct7 [6:0] $end
$var wire 3 < funct3 [2:0] $end
$var wire 1 = branch $end
$var wire 1 > alu_zero $end
$var wire 128 ? alu_result [127:0] $end
$var wire 4 @ alu_op [3:0] $end
$var reg 128 A alu_a [127:0] $end
$var reg 128 B alu_b [127:0] $end
$var reg 1 C branch_taken $end
$var reg 128 D branch_target [127:0] $end
$var reg 128 E dmem_addr [127:0] $end
$var reg 1 ( dmem_valid $end
$var reg 128 F dmem_wdata [127:0] $end
$var reg 1 & dmem_we $end
$var reg 1 % halt_reg $end
$var reg 128 G imm_b [127:0] $end
$var reg 128 H imm_i [127:0] $end
$var reg 128 I imm_j [127:0] $end
$var reg 128 J imm_s [127:0] $end
$var reg 128 K imm_u [127:0] $end
$var reg 128 L writeback_data [127:0] $end
$scope module u_alu $end
$var wire 128 M a [127:0] $end
$var wire 128 N b [127:0] $end
$var wire 4 O op [3:0] $end
$var parameter 4 P ALU_ADD $end
$var parameter 4 Q ALU_AND $end
$var parameter 4 R ALU_OR $end
$var parameter 4 S ALU_SLL $end
$var parameter 4 T ALU_SRL $end
$var parameter 4 U ALU_SUB $end
$var parameter 4 V ALU_XOR $end
$var reg 128 W y [127:0] $end
$var reg 1 > zero $end
$upscope $end
$scope module u_decoder $end
$var wire 32 X instr [31:0] $end
$var parameter 4 Y ALU_ADD $end
$var parameter 4 Z ALU_AND $end
$var parameter 4 [ ALU_OR $end
$var parameter 4 \ ALU_SUB $end
$var parameter 4 ] ALU_XOR $end
$var reg 4 ^ alu_op [3:0] $end
$var reg 1 = branch $end
$var reg 3 _ funct3 [2:0] $end
$var reg 7 ` funct7 [6:0] $end
$var reg 1 : jump $end
$var reg 1 9 mem_read $end
$var reg 1 8 mem_write $end
$var reg 7 a opcode [6:0] $end
$var reg 5 b rd [4:0] $end
$var reg 1 4 reg_write $end
$var reg 5 c rs1 [4:0] $end
$var reg 5 d rs2 [4:0] $end
$upscope $end
$scope module u_pc $end
$var wire 1 C branch_taken $end
$var wire 128 e branch_target [127:0] $end
$var wire 1 * clk $end
$var wire 1 f enable $end
$var wire 1 + rst $end
$var parameter 128 g RESET_PC $end
$var reg 128 h pc [127:0] $end
$upscope $end
$scope module u_regfile $end
$var wire 1 * clk $end
$var wire 5 i rd_addr [4:0] $end
$var wire 128 j rd_data [127:0] $end
$var wire 5 k rs1_addr [4:0] $end
$var wire 5 l rs2_addr [4:0] $end
$var wire 1 + rst $end
$var wire 1 m wr_en $end
$var wire 128 n rs2_data [127:0] $end
$var wire 128 o rs1_data [127:0] $end
$var integer 32 p i [31:0] $end
$upscope $end
$upscope $end
$scope begin $unm_blk_2 $end
$var integer 32 q i [31:0] $end
$upscope $end
$upscope $end
$enddefinitions $end
$comment Show the parameter values. $end
$dumpall
b0 g
b100 ]
b1 \
b11 [
b10 Z
b0 Y
b100 V
b1 U
b110 T
b101 S
b11 R
b10 Q
b0 P
$end
#0
$dumpvars
b100000 q
bx p
bx o
bx n
0m
bx l
bx k
bx j
bx i
bx h
xf
bx e
bx d
bx c
bx b
bx a
bx `
bx _
b0 ^
bx X
bx W
b0 O
bx N
bx M
bx L
bx000000000000 K
bx J
bx0 I
bx H
bx0 G
b0 F
b0 E
bx D
0C
bx B
bx A
b0 @
bx ?
x>
0=
bx <
bx ;
0:
09
08
bx 7
bx 6
bx 5
04
bx 3
bx 2
bx 1
bx 0
bx /
bx .
bx -
b0 ,
1+
0*
b0 )
0(
b0 '
0&
x%
bx $
bx #
0"
b0 !
$end
#5000
b1010 L
b1010 j
0>
b1010 ?
b1010 W
1m
b0 A
b0 M
b0 0
b0 n
b0 2
b0 o
b1010 B
b1010 N
14
b0 ;
b0 `
b1010 1
b1010 d
b1010 l
b0 3
b0 c
b0 k
b0 <
b0 _
b1 5
b1 b
b1 i
b10011 7
b10011 a
b1010 I
b101000000000000000000000 K
b100000000000 G
b1 J
b1010 H
b101000000000000010010011 /
b101000000000000010010011 X
b101000000000000010010011 #
b101000000000000010010011 .
b100 D
b100 e
b0 $
b0 -
b0 6
b0 h
1f
0%
b100000 p
1*
#10000
0*
#15000
b100000 p
1*
#16000
0+
#20000
0*
#25000
b101 L
b101 j
b101 ?
b101 W
14
b101 1
b101 d
b101 l
b10 5
b10 b
b10 i
b100000000100 I
b10100000000000000000000 K
b10 G
b10 J
b101 H
b10100000000000100010011 /
b10100000000000100010011 X
b10100000000000100010011 #
b10100000000000100010011 .
b101 B
b101 N
b1000 D
b1000 e
b100 $
b100 -
b100 6
b100 h
1*
#30000
0*
#35000
b1111 L
b1111 j
b101 0
b101 n
b1010 A
b1010 M
0>
b1111 ?
b1111 W
b1010 2
b1010 o
14
b10 1
b10 d
b10 l
b1 3
b1 c
b1 k
b11 5
b11 b
b11 i
b110011 7
b110011 a
b1000000000000010 I
b1000001000000000000000 K
b100000000010 G
b11 J
b10 H
b1000001000000110110011 /
b1000001000000110110011 X
b1000001000000110110011 #
b1000001000000110110011 .
b101 B
b101 N
b1100 D
b1100 e
b1000 $
b1000 -
b1000 6
b1000 h
1*
#40000
0*
#45000
b1010 L
b1010 j
b1010 B
b1010 N
b1010 ?
b1010 W
0m
b1010 0
b1010 n
b0 A
b0 M
b0 2
b0 o
04
b1 1
b1 d
b1 l
b0 3
b0 c
b0 k
b0 5
b0 b
b0 i
b1110011 7
b1110011 a
b100000000000 I
b100000000000000000000 K
b0 G
b0 J
b1 H
b100000000000001110011 /
b100000000000001110011 X
b100000000000001110011 #
b100000000000001110011 .
b10000 D
b10000 e
b1100 $
b1100 -
b1100 6
b1100 h
1*
#50000
0*
#55000
b0 L
b0 j
1>
b0 ?
b0 W
b0 0
b0 n
b0 B
b0 N
14
b0 1
b0 d
b0 l
b10011 7
b10011 a
b0 I
b0 K
b0 H
b10011 /
b10011 X
b10011 #
b10011 .
b10100 D
b10100 e
0f
1%
b10000 $
b10000 -
b10000 6
b10000 h
1*
